exeception_to_teams/__init__.py
exeception_to_teams/apps.py
exeception_to_teams/middlewares.py
exeception_to_teams/migrations/__init__.py
exeception_to_teams-0.0.3.dist-info/LICENCE
exeception_to_teams-0.0.3.dist-info/METADATA
exeception_to_teams-0.0.3.dist-info/WHEEL
exeception_to_teams-0.0.3.dist-info/top_level.txt
exeception_to_teams-0.0.3.dist-info/RECORD
