Metadata-Version: 2.1
Name: exeception-to-teams
Version: 0.0.3
Summary: Notification/Alert for django users
Author: Ideabreed Technology (Milann Malla)
Author-email: <hello@itsmilann.com>
Project-URL: exception to teams, https://github.com/ItsMilann/exeception-to-teams/tree/release
Keywords: python,django,middleware,exception,ideabreed,teams,microsoft
Classifier: Development Status :: 1 - Planning
Classifier: Intended Audience :: Developers
Classifier: Programming Language :: Python :: 3.10
Classifier: Operating System :: Unix
Classifier: Operating System :: MacOS :: MacOS X
Classifier: Operating System :: Microsoft :: Windows
License-File: LICENCE
Requires-Dist: requests
Requires-Dist: django
